{"type": "FeatureCollection", "features": [{"id": "0", "type": "Feature", "properties": {"OBJECTID": 70882, "FIRE_NUMBER": "2025443", "FIRE_NUMBER_SHORT": "443", "FIRE_NAME": "Sphagnum Pile", "DEGREES_LAT": 46.69345, "DEGREES_LONG": 65.41237, "FIRE_STAT_ID": 3.0, "FIRE_STAT_DESC_E": "Under Control", "FIRE_STAT_DESC_F": "Maîtrisé ", "FIRE_SIZE": 0.1, "TIME_DETECTED": 1763528400000, "FIRE_STAT_DATE": 1763553600000, "FIRE_OF_NOTE_INDCTR": 0, "FIRE_NOTE_ENG": "No", "FIRE_NOTE_FR": "Non", "PERCENT_CONTAINED": 100.0}, "geometry": {"type": "Point", "coordinates": [-65.41236874009421, 46.69345958854781]}}], "archived_at": "2025-11-20 05:30:33 AST"}
