{
  "type": "FeatureCollection",
  "features": [
    {
      "type": "Feature",
      "id": 71002,
      "geometry": {
        "type": "Point",
        "coordinates": [
          -66.77096916414115,
          45.68562938241671
        ]
      },
      "properties": {
        "OBJECTID": 71002,
        "FIRE_NAME": "001",
        "DEGREES_LAT": 45.68562,
        "DEGREES_LONG": 66.77096999999999,
        "FIRE_STAT_ID": 1,
        "FIRE_STAT_DESC_E": "Out of Control",
        "FIRE_STAT_DESC_F": "Hors contrôle",
        "FIRE_SIZE": 0.10000000149011612,
        "TIME_DETECTED": 1774379580000,
        "FIRE_STAT_DATE": 1774384200000,
        "FIRE_OF_NOTE_INDCTR": 0,
        "FIRE_NOTE_ENG": "No",
        "FIRE_NOTE_FR": "Non",
        "FETCHED_FROM_ERD": 1774960812
      }
    }
  ],
  "crs": {
    "type": "name",
    "properties": {
      "name": "EPSG:4326"
    }
  },
  "archived_at": "2026-03-24 (backfilled)"
}
