{"type": "FeatureCollection", "features": [{"type": "Feature", "id": 75322, "geometry": {"type": "Point", "coordinates": [-66.44586906124741, 45.889979426468734]}, "properties": {"OBJECTID": 75322, "FIRE_NAME": "Rush Lake", "DEGREES_LAT": 45.88997, "DEGREES_LONG": 66.44587, "FIRE_STAT_ID": 1, "FIRE_STAT_DESC_E": "Out of Control", "FIRE_STAT_DESC_F": "Hors contrôle", "FIRE_SIZE": 10, "TIME_DETECTED": 1784823900000, "FIRE_STAT_DATE": 1784847720000, "FIRE_OF_NOTE_INDCTR": 0, "FIRE_NOTE_ENG": "No", "FIRE_NOTE_FR": "Non", "PERCENT_CONTAINED": 10, "FIRE_NUMBER_SHORT": "318"}}], "crs": {"type": "name", "properties": {"name": "EPSG:4326"}}, "archived_at": "2026-07-24 06:59:08 ADT"}
